mypackage/__init__.py
mypackage/mymodule.py
tests/__init__.py
tests/test_mymodule.py
ksj_package-0.1.0.dist-info/LICENSE
ksj_package-0.1.0.dist-info/METADATA
ksj_package-0.1.0.dist-info/WHEEL
ksj_package-0.1.0.dist-info/top_level.txt
ksj_package-0.1.0.dist-info/RECORD
