Metadata-Version: 2.1
Name: ksj-package
Version: 0.1.0
Summary: A simple example package
Home-page: https://github.com/seongjae/mypackage
Author: seongjae
Author-email: ksjeans@naver.com
Classifier: Programming Language :: Python :: 3
Classifier: License :: OSI Approved :: MIT License
Classifier: Operating System :: OS Independent
Requires-Python: >=3.6
License-File: LICENSE
